ovos_stt_plugin_whisper_lm/__init__.py
ovos_stt_plugin_whisper_lm/version.py
ovos_stt_plugin_whisper_lm-0.0.5.dist-info/LICENSE
ovos_stt_plugin_whisper_lm-0.0.5.dist-info/METADATA
ovos_stt_plugin_whisper_lm-0.0.5.dist-info/WHEEL
ovos_stt_plugin_whisper_lm-0.0.5.dist-info/entry_points.txt
ovos_stt_plugin_whisper_lm-0.0.5.dist-info/top_level.txt
ovos_stt_plugin_whisper_lm-0.0.5.dist-info/zip-safe
ovos_stt_plugin_whisper_lm-0.0.5.dist-info/RECORD
