Metadata-Version: 2.1
Name: ovos-stt-plugin-whisper-lm
Version: 0.0.5
Summary: A whisper stt plugin for OVOS
Home-page: https://github.com/OpenVoiceOS/ovos-stt-plugin-whisper-lm
Author: JarbasAi
Author-email: jarbasai@mailfence.com
License: Apache-2.0
Keywords: mycroft ovos plugin stt
Classifier: Development Status :: 3 - Alpha
Classifier: Intended Audience :: Developers
Classifier: Topic :: Text Processing :: Linguistic
Classifier: License :: OSI Approved :: Apache Software License
License-File: LICENSE
Requires-Dist: ovos-plugin-manager<2.0.0,>=1.0.0
Requires-Dist: SpeechRecognition>=3.8.1
Requires-Dist: requests
Requires-Dist: transformers
Requires-Dist: kenlm
Requires-Dist: whisper-lm-transformers
